finops_crawler/__init__.py
finops_crawler/aws/README.md
finops_crawler/aws/__init__.py
finops_crawler/aws/api.py
finops_crawler/aws/example.py
finops_crawler/azure/README.md
finops_crawler/azure/__init__.py
finops_crawler/azure/api.py
finops_crawler/azure/example.py
finops_crawler/base.py
finops_crawler/credentials_provider/__init__.py
finops_crawler/credentials_provider/credentials_config.yml
finops_crawler/credentials_provider/credentials_provider.py
finops_crawler/openai/README.md
finops_crawler/openai/__init__.py
finops_crawler/openai/api.py
finops_crawler/openai/example.py
finops_crawler-0.1.18.dist-info/LICENSE
finops_crawler-0.1.18.dist-info/METADATA
finops_crawler-0.1.18.dist-info/WHEEL
finops_crawler-0.1.18.dist-info/RECORD
