Metadata-Version: 2.1
Name: finops_crawler
Version: 0.1.18
Summary: It's a package for importing cost and usage data from various cloud platforms and SaaS tools
Author: Lauri Koobas
Author-email: laurikoobas@gmail.com
Requires-Python: >=3.10,<4.0
Classifier: Programming Language :: Python :: 3
Classifier: Programming Language :: Python :: 3.10
Classifier: Programming Language :: Python :: 3.11
Requires-Dist: PyYAML (>=6.0.1,<7.0.0)
Requires-Dist: boto3 (==1.26.156)
Requires-Dist: requests (>=2.31.0,<3.0.0)
Project-URL: Documentation, https://github.com/finops-fitness-club/finops_crawler#readme
Project-URL: Home, https://github.com/finops-fitness-club/finops_crawler
Project-URL: Repository, https://github.com/finops-fitness-club/finops_crawler.git
